<?xml version="1.0" encoding="UTF-8"?>
<billStatus>
  <bill>
    <cosponsors>
      <item>
        <state>CA</state>
        <lastName>Lieu</lastName>
        <fullName>Rep. Lieu, Ted [D-CA-33]</fullName>
        <sponsorshipWithdrawnDate />
        <middleName />
        <firstName>Ted</firstName>
        <identifiers>
          <gpoId />
          <lisID>2230</lisID>
          <bioguideId>L000582</bioguideId>
        </identifiers>
        <district>33</district>
        <party>D</party>
        <bioguideId>L000582</bioguideId>
        <sponsorshipDate>2017-06-13</sponsorshipDate>
        <isOriginalCosponsor>False</isOriginalCosponsor>
      </item>
      <item>
        <state>NY</state>
        <lastName>Clarke</lastName>
        <fullName>Rep. Clarke, Yvette D. [D-NY-9]</fullName>
        <sponsorshipWithdrawnDate />
        <middleName>D.</middleName>
        <firstName>Yvette</firstName>
        <identifiers>
          <gpoId>8072</gpoId>
          <bioguideId>C001067</bioguideId>
          <lisID>1864</lisID>
        </identifiers>
        <district>9</district>
        <party>D</party>
        <bioguideId>C001067</bioguideId>
        <sponsorshipDate>2017-06-13</sponsorshipDate>
        <isOriginalCosponsor>False</isOriginalCosponsor>
      </item>
      <item>
        <state>IL</state>
        <lastName>Lipinski</lastName>
        <fullName>Rep. Lipinski, Daniel [D-IL-3]</fullName>
        <sponsorshipWithdrawnDate />
        <middleName>William</middleName>
        <firstName>Daniel</firstName>
        <identifiers>
          <lisID>1781</lisID>
          <bioguideId>L000563</bioguideId>
          <gpoId>7923</gpoId>
        </identifiers>
        <district>3</district>
        <party>D</party>
        <bioguideId>L000563</bioguideId>
        <sponsorshipDate>2017-06-13</sponsorshipDate>
        <isOriginalCosponsor>False</isOriginalCosponsor>
      </item>
      <item>
        <state>OR</state>
        <lastName>DEFAZIO</lastName>
        <fullName>Rep. DeFazio, Peter A. [D-OR-4]</fullName>
        <sponsorshipWithdrawnDate />
        <middleName>A.</middleName>
        <firstName>PETER</firstName>
        <identifiers>
          <lisID>279</lisID>
          <gpoId>8117</gpoId>
          <bioguideId>D000191</bioguideId>
        </identifiers>
        <district>4</district>
        <party>D</party>
        <bioguideId>D000191</bioguideId>
        <sponsorshipDate>2017-06-13</sponsorshipDate>
        <isOriginalCosponsor>False</isOriginalCosponsor>
      </item>
      <item>
        <state>NY</state>
        <lastName>MEEKS</lastName>
        <fullName>Rep. Meeks, Gregory W. [D-NY-5]</fullName>
        <sponsorshipWithdrawnDate />
        <middleName>W.</middleName>
        <firstName>GREGORY</firstName>
        <identifiers>
          <bioguideId>M001137</bioguideId>
          <lisID>1506</lisID>
          <gpoId>8067</gpoId>
        </identifiers>
        <district>5</district>
        <party>D</party>
        <bioguideId>M001137</bioguideId>
        <sponsorshipDate>2017-06-13</sponsorshipDate>
        <isOriginalCosponsor>False</isOriginalCosponsor>
      </item>
      <item>
        <state>MN</state>
        <lastName>MCCOLLUM</lastName>
        <fullName>Rep. McCollum, Betty [D-MN-4]</fullName>
        <sponsorshipWithdrawnDate />
        <middleName />
        <firstName>BETTY</firstName>
        <identifiers>
          <bioguideId>M001143</bioguideId>
          <lisID>1653</lisID>
          <gpoId>8004</gpoId>
        </identifiers>
        <district>4</district>
        <party>D</party>
        <bioguideId>M001143</bioguideId>
        <sponsorshipDate>2017-06-13</sponsorshipDate>
        <isOriginalCosponsor>False</isOriginalCosponsor>
      </item>
      <item>
        <state>FL</state>
        <lastName>Soto</lastName>
        <fullName>Rep. Soto, Darren [D-FL-9]</fullName>
        <sponsorshipWithdrawnDate />
        <middleName />
        <firstName>Darren</firstName>
        <identifiers>
          <gpoId />
          <lisID>2319</lisID>
          <bioguideId>S001200</bioguideId>
        </identifiers>
        <district>9</district>
        <party>D</party>
        <bioguideId>S001200</bioguideId>
        <sponsorshipDate>2017-06-13</sponsorshipDate>
        <isOriginalCosponsor>False</isOriginalCosponsor>
      </item>
      <item>
        <state>CA</state>
        <lastName>LEE</lastName>
        <fullName>Rep. Lee, Barbara [D-CA-13]</fullName>
        <sponsorshipWithdrawnDate />
        <middleName />
        <firstName>BARBARA</firstName>
        <identifiers>
          <gpoId>7814</gpoId>
          <lisID>1501</lisID>
          <bioguideId>L000551</bioguideId>
        </identifiers>
        <district>13</district>
        <party>D</party>
        <bioguideId>L000551</bioguideId>
        <sponsorshipDate>2017-06-13</sponsorshipDate>
        <isOriginalCosponsor>False</isOriginalCosponsor>
      </item>
      <item>
        <state>TN</state>
        <lastName>Cohen</lastName>
        <fullName>Rep. Cohen, Steve [D-TN-9]</fullName>
        <sponsorshipWithdrawnDate />
        <middleName />
        <firstName>Steve</firstName>
        <identifiers>
          <lisID>1878</lisID>
          <bioguideId>C001068</bioguideId>
          <gpoId>8156</gpoId>
        </identifiers>
        <district>9</district>
        <party>D</party>
        <bioguideId>C001068</bioguideId>
        <sponsorshipDate>2017-06-13</sponsorshipDate>
        <isOriginalCosponsor>False</isOriginalCosponsor>
      </item>
      <item>
        <state>MO</state>
        <lastName>CLAY</lastName>
        <fullName>Rep. Clay, Wm. Lacy [D-MO-1]</fullName>
        <sponsorshipWithdrawnDate />
        <middleName>LACY</middleName>
        <firstName>WM.</firstName>
        <identifiers>
          <lisID>1654</lisID>
          <bioguideId>C001049</bioguideId>
          <gpoId>8009</gpoId>
        </identifiers>
        <district>1</district>
        <party>D</party>
        <bioguideId>C001049</bioguideId>
        <sponsorshipDate>2017-06-13</sponsorshipDate>
        <isOriginalCosponsor>False</isOriginalCosponsor>
      </item>
      <item>
        <state>CA</state>
        <lastName>Costa</lastName>
        <fullName>Rep. Costa, Jim [D-CA-16]</fullName>
        <sponsorshipWithdrawnDate />
        <middleName />
        <firstName>Jim</firstName>
        <identifiers>
          <bioguideId>C001059</bioguideId>
          <lisID>1774</lisID>
          <gpoId>7825</gpoId>
        </identifiers>
        <district>16</district>
        <party>D</party>
        <bioguideId>C001059</bioguideId>
        <sponsorshipDate>2017-06-15</sponsorshipDate>
        <isOriginalCosponsor>False</isOriginalCosponsor>
      </item>
      <item>
        <state>IL</state>
        <lastName>RUSH</lastName>
        <fullName>Rep. Rush, Bobby L. [D-IL-1]</fullName>
        <sponsorshipWithdrawnDate />
        <middleName>L.</middleName>
        <firstName>BOBBY</firstName>
        <identifiers>
          <gpoId>7921</gpoId>
          <bioguideId>R000515</bioguideId>
          <lisID>1003</lisID>
        </identifiers>
        <district>1</district>
        <party>D</party>
        <bioguideId>R000515</bioguideId>
        <sponsorshipDate>2017-06-15</sponsorshipDate>
        <isOriginalCosponsor>False</isOriginalCosponsor>
      </item>
      <item>
        <state>NY</state>
        <lastName>NADLER</lastName>
        <fullName>Rep. Nadler, Jerrold [D-NY-10]</fullName>
        <sponsorshipWithdrawnDate />
        <middleName />
        <firstName>JERROLD</firstName>
        <identifiers>
          <lisID>850</lisID>
          <gpoId>8069</gpoId>
          <bioguideId>N000002</bioguideId>
        </identifiers>
        <district>10</district>
        <party>D</party>
        <bioguideId>N000002</bioguideId>
        <sponsorshipDate>2017-06-15</sponsorshipDate>
        <isOriginalCosponsor>False</isOriginalCosponsor>
      </item>
      <item>
        <state>IL</state>
        <lastName>GUTIERREZ</lastName>
        <fullName>Rep. Gutierrez, Luis V. [D-IL-4]</fullName>
        <sponsorshipWithdrawnDate />
        <middleName>V.</middleName>
        <firstName>LUIS</firstName>
        <identifiers>
          <lisID>478</lisID>
          <bioguideId>G000535</bioguideId>
          <gpoId>7924</gpoId>
        </identifiers>
        <district>4</district>
        <party>D</party>
        <bioguideId>G000535</bioguideId>
        <sponsorshipDate>2017-06-15</sponsorshipDate>
        <isOriginalCosponsor>False</isOriginalCosponsor>
      </item>
      <item>
        <state>IL</state>
        <lastName>DAVIS</lastName>
        <fullName>Rep. Davis, Danny K. [D-IL-7]</fullName>
        <sponsorshipWithdrawnDate />
        <middleName>K.</middleName>
        <firstName>DANNY</firstName>
        <identifiers>
          <lisID>1477</lisID>
          <bioguideId>D000096</bioguideId>
          <gpoId>7927</gpoId>
        </identifiers>
        <district>7</district>
        <party>D</party>
        <bioguideId>D000096</bioguideId>
        <sponsorshipDate>2017-06-15</sponsorshipDate>
        <isOriginalCosponsor>False</isOriginalCosponsor>
      </item>
      <item>
        <state>NY</state>
        <lastName>Jeffries</lastName>
        <fullName>Rep. Jeffries, Hakeem S. [D-NY-8]</fullName>
        <sponsorshipWithdrawnDate />
        <middleName>S.</middleName>
        <firstName>Hakeem</firstName>
        <identifiers>
          <bioguideId>J000294</bioguideId>
          <lisID>2149</lisID>
          <gpoId />
        </identifiers>
        <district>8</district>
        <party>D</party>
        <bioguideId>J000294</bioguideId>
        <sponsorshipDate>2017-06-15</sponsorshipDate>
        <isOriginalCosponsor>False</isOriginalCosponsor>
      </item>
      <item>
        <state>MA</state>
        <lastName>MCGOVERN</lastName>
        <fullName>Rep. McGovern, James P. [D-MA-2]</fullName>
        <sponsorshipWithdrawnDate />
        <middleName>P.</middleName>
        <firstName>JAMES</firstName>
        <identifiers>
          <bioguideId>M000312</bioguideId>
          <lisID>1504</lisID>
          <gpoId>7968</gpoId>
        </identifiers>
        <district>2</district>
        <party>D</party>
        <bioguideId>M000312</bioguideId>
        <sponsorshipDate>2017-06-22</sponsorshipDate>
        <isOriginalCosponsor>False</isOriginalCosponsor>
      </item>
      <item>
        <state>IL</state>
        <lastName>SCHAKOWSKY</lastName>
        <fullName>Rep. Schakowsky, Janice D. [D-IL-9]</fullName>
        <sponsorshipWithdrawnDate />
        <middleName>D.</middleName>
        <firstName>JANICE</firstName>
        <identifiers>
          <lisID>1588</lisID>
          <gpoId>7929</gpoId>
          <bioguideId>S001145</bioguideId>
        </identifiers>
        <district>9</district>
        <party>D</party>
        <bioguideId>S001145</bioguideId>
        <sponsorshipDate>2017-06-22</sponsorshipDate>
        <isOriginalCosponsor>False</isOriginalCosponsor>
      </item>
      <item>
        <state>NJ</state>
        <lastName>PALLONE</lastName>
        <fullName>Rep. Pallone, Frank, Jr. [D-NJ-6]</fullName>
        <sponsorshipWithdrawnDate />
        <middleName />
        <firstName>FRANK</firstName>
        <identifiers>
          <gpoId>8048</gpoId>
          <lisID>887</lisID>
          <bioguideId>P000034</bioguideId>
        </identifiers>
        <district>6</district>
        <party>D</party>
        <bioguideId>P000034</bioguideId>
        <sponsorshipDate>2017-06-22</sponsorshipDate>
        <isOriginalCosponsor>False</isOriginalCosponsor>
      </item>
      <item>
        <state>IL</state>
        <lastName>Schneider</lastName>
        <fullName>Rep. Schneider, Bradley Scott [D-IL-10]</fullName>
        <sponsorshipWithdrawnDate />
        <middleName>Scott</middleName>
        <firstName>Bradley</firstName>
        <identifiers>
          <bioguideId>S001190</bioguideId>
          <lisID>2124</lisID>
          <gpoId />
        </identifiers>
        <district>10</district>
        <party>D</party>
        <bioguideId>S001190</bioguideId>
        <sponsorshipDate>2017-06-22</sponsorshipDate>
        <isOriginalCosponsor>False</isOriginalCosponsor>
      </item>
      <item>
        <state>OH</state>
        <lastName>KAPTUR</lastName>
        <fullName>Rep. Kaptur, Marcy [D-OH-9]</fullName>
        <sponsorshipWithdrawnDate />
        <middleName />
        <firstName>MARCY</firstName>
        <identifiers>
          <gpoId>8099</gpoId>
          <lisID>616</lisID>
          <bioguideId>K000009</bioguideId>
        </identifiers>
        <district>9</district>
        <party>D</party>
        <bioguideId>K000009</bioguideId>
        <sponsorshipDate>2017-07-20</sponsorshipDate>
        <isOriginalCosponsor>False</isOriginalCosponsor>
      </item>
      <item>
        <state>MA</state>
        <lastName>Tsongas</lastName>
        <fullName>Rep. Tsongas, Niki [D-MA-3]</fullName>
        <sponsorshipWithdrawnDate />
        <middleName />
        <firstName>Niki</firstName>
        <identifiers>
          <gpoId>7970</gpoId>
          <lisID>1884</lisID>
          <bioguideId>T000465</bioguideId>
        </identifiers>
        <district>3</district>
        <party>D</party>
        <bioguideId>T000465</bioguideId>
        <sponsorshipDate>2017-07-20</sponsorshipDate>
        <isOriginalCosponsor>False</isOriginalCosponsor>
      </item>
      <item>
        <state>HI</state>
        <lastName>Hanabusa</lastName>
        <fullName>Rep. Hanabusa, Colleen [D-HI-1]</fullName>
        <sponsorshipWithdrawnDate />
        <middleName />
        <firstName>Colleen</firstName>
        <identifiers>
          <lisID>2010</lisID>
          <gpoId>7912</gpoId>
          <bioguideId>H001050</bioguideId>
        </identifiers>
        <district>1</district>
        <party>D</party>
        <bioguideId>H001050</bioguideId>
        <sponsorshipDate>2017-07-20</sponsorshipDate>
        <isOriginalCosponsor>False</isOriginalCosponsor>
      </item>
    </cosponsors>
    <committees>
      <billCommittees>
        <item>
          <activities>
            <item>
              <date>2017-06-12T16:00:39Z</date>
              <name>Referred to</name>
            </item>
          </activities>
          <subcommittees />
          <name>Oversight and Government Reform Committee</name>
          <type>Standing</type>
          <systemCode>hsgo00</systemCode>
          <chamber>House</chamber>
        </item>
      </billCommittees>
    </committees>
    <title>COVFEFE Act of 2017</title>
    <titles>
      <item>
        <titleType>(Extracted from GPO) Short Titles as Introduced</titleType>
        <parentTitleType />
        <title>COVFEFE Act of 2017</title>
        <chamberName />
        <chamberCode />
      </item>
      <item>
        <titleType>(Extracted from GPO) Short Titles as Introduced</titleType>
        <parentTitleType />
        <title>Communications Over Various Feeds Electronically For Engagement Act of 2017</title>
        <chamberName />
        <chamberCode />
      </item>
      <item>
        <titleType>Short Titles as Introduced</titleType>
        <parentTitleType />
        <title>COVFEFE Act of 2017</title>
        <chamberName />
        <chamberCode />
      </item>
      <item>
        <titleType>Short Titles as Introduced</titleType>
        <parentTitleType />
        <title>Communications Over Various Feeds Electronically For Engagement Act of 2017</title>
        <chamberName />
        <chamberCode />
      </item>
      <item>
        <titleType>Official Title as Introduced</titleType>
        <parentTitleType />
        <title>To amend section 2201 of title 44, United States Code, to require the preservation of Presidential social media accounts, and for other purposes.</title>
        <chamberName />
        <chamberCode />
      </item>
      <item>
        <titleType>Display Title</titleType>
        <parentTitleType />
        <title>COVFEFE Act of 2017</title>
        <chamberName />
        <chamberCode />
      </item>
    </titles>
    <congress>115</congress>
    <createDate>2017-06-13T03:11:38Z</createDate>
    <calendarNumbers />
    <committeeReports />
    <recordedVotes />
    <relatedBills />
    <laws />
    <billNumber>2884</billNumber>
    <summaries>
      <billSummaries />
    </summaries>
    <billType>HR</billType>
    <subjects>
      <billSubjects>
        <policyArea>
          <name>Government Operations and Politics</name>
        </policyArea>
        <legislativeSubjects />
      </billSubjects>
    </subjects>
    <version>1.0.0</version>
    <sponsors>
      <item>
        <fullName>Rep. Quigley, Mike [D-IL-5]</fullName>
        <bioguideId>Q000023</bioguideId>
        <lastName>Quigley</lastName>
        <middleName />
        <identifiers>
          <gpoId>7925</gpoId>
          <lisID>1967</lisID>
          <bioguideId>Q000023</bioguideId>
        </identifiers>
        <district>5</district>
        <state>IL</state>
        <firstName>Mike</firstName>
        <byRequestType />
        <party>D</party>
      </item>
    </sponsors>
    <constitutionalAuthorityStatementText><![CDATA[<pre>From the Congressional Record Online through the Government Publishing Office [<a href='http://www.gpo.gov'>www.gpo.gov</a>]By Mr. QUIGLEY:H.R. 2884.Congress has the power to enact this legislation pursuantto the following:Article 1, Section 8, Clause 3 of the U.S. Constitution[Page H4855]</pre>]]></constitutionalAuthorityStatementText>
    <notes />
    <actions>
      <actionByCounts>
        <houseOfRepresentatives>3</houseOfRepresentatives>
      </actionByCounts>
      <actionTypeCounts>
        <introducedInTheHouse>1</introducedInTheHouse>
        <introducedInHouse>1</introducedInHouse>
        <billReferrals>1</billReferrals>
      </actionTypeCounts>
      <item>
        <text>Referred to the House Committee on Oversight and Government Reform.</text>
        <type>IntroReferral</type>
        <actionDate>2017-06-12</actionDate>
        <actionCode>H11100</actionCode>
        <links />
        <sourceSystem>
          <code>2</code>
          <name>House floor actions</name>
        </sourceSystem>
        <committee>
          <systemCode>hsgo00</systemCode>
          <name>Oversight and Government Reform Committee</name>
        </committee>
      </item>
      <item>
        <text>Introduced in House</text>
        <type>IntroReferral</type>
        <actionDate>2017-06-12</actionDate>
        <actionCode>Intro-H</actionCode>
        <links />
        <sourceSystem>
          <code>9</code>
          <name>Library of Congress</name>
        </sourceSystem>
        <committee />
      </item>
      <item>
        <text>Introduced in House</text>
        <type>IntroReferral</type>
        <actionDate>2017-06-12</actionDate>
        <actionCode>1000</actionCode>
        <links />
        <sourceSystem>
          <code>9</code>
          <name>Library of Congress</name>
        </sourceSystem>
        <committee />
      </item>
    </actions>
    <amendments />
    <updateDate>2017-07-21T07:16:22Z</updateDate>
    <cboCostEstimates />
    <originChamber>House</originChamber>
    <policyArea>
      <name>Government Operations and Politics</name>
    </policyArea>
    <latestAction>
      <text>Referred to the House Committee on Oversight and Government Reform.</text>
      <actionDate>2017-06-12</actionDate>
      <links />
    </latestAction>
    <introducedDate>2017-06-12</introducedDate>
  </bill>
  <dublinCore xmlns:dc="http://purl.org/dc/elements/1.1/">
    <dc:format>text/xml</dc:format>
    <dc:language>EN</dc:language>
    <dc:rights>Pursuant to Title 17 Section 105 of the United States Code, this file is not subject to copyright protection and is in the public domain.</dc:rights>
    <dc:contributor>Congressional Research Service, Library of Congress</dc:contributor>
    <dc:description>This file contains bill summaries and statuses for federal legislation. A bill summary describes the most significant provisions of a piece of legislation and details the effects the legislative text may have on current law and federal programs. Bill summaries are authored by the Congressional Research Service (CRS) of the Library of Congress. As stated in Public Law 91-510 (2 USC 166 (d)(6)), one of the duties of CRS is "to prepare summaries and digests of bills and resolutions of a public general nature introduced in the Senate or House of Representatives". For more information, refer to the User Guide that accompanies this file.</dc:description>
  </dublinCore>
</billStatus>

