{
  "actions": [
    {
      "acted_at": "2017-05-04", 
      "action_code": "Intro-H", 
      "references": [], 
      "text": "Introduced in House", 
      "type": "action"
    }, 
    {
      "acted_at": "2017-05-04", 
      "action_code": "H11100", 
      "committees": [
        "HSED"
      ], 
      "references": [], 
      "status": "REFERRED", 
      "text": "Referred to the House Committee on Education and the Workforce.", 
      "type": "referral"
    }
  ], 
  "amendments": [], 
  "bill_id": "hr2382-115", 
  "bill_type": "hr", 
  "by_request": false, 
  "committee_reports": [], 
  "committees": [
    {
      "activity": [
        "referral"
      ], 
      "committee": "House Education and the Workforce", 
      "committee_id": "HSED"
    }
  ], 
  "congress": "115", 
  "cosponsors": [], 
  "enacted_as": null, 
  "history": {
    "active": false, 
    "awaiting_signature": false, 
    "enacted": false, 
    "vetoed": false
  }, 
  "introduced_at": "2017-05-04", 
  "number": "2382", 
  "official_title": "To amend the Richard B. Russell National School Lunch Act and the Child Nutrition Act of 1966 to eliminate certain Federal nutrition requirements, and for other purposes.", 
  "popular_title": null, 
  "related_bills": [], 
  "short_title": "Permanent Flexibility for School Meals Act", 
  "sponsor": {
    "bioguide_id": "N000184", 
    "district": null, 
    "name": "Noem, Kristi L.", 
    "state": "SD", 
    "title": "Rep", 
    "type": "person"
  }, 
  "status": "REFERRED", 
  "status_at": "2017-05-04", 
  "subjects": [
    "Agriculture and food"
  ], 
  "subjects_top_term": "Agriculture and food", 
  "summary": null, 
  "titles": [
    {
      "as": "introduced", 
      "is_for_portion": false, 
      "title": "Permanent Flexibility for School Meals Act", 
      "type": "short"
    }, 
    {
      "as": "introduced", 
      "is_for_portion": false, 
      "title": "Permanent Flexibility for School Meals Act", 
      "type": "short"
    }, 
    {
      "as": "introduced", 
      "is_for_portion": false, 
      "title": "To amend the Richard B. Russell National School Lunch Act and the Child Nutrition Act of 1966 to eliminate certain Federal nutrition requirements, and for other purposes.", 
      "type": "official"
    }, 
    {
      "as": null, 
      "is_for_portion": false, 
      "title": "Permanent Flexibility for School Meals Act", 
      "type": "display"
    }
  ], 
  "updated_at": "2017-06-19T22:15:24Z", 
  "url": "https://www.gpo.gov/fdsys/bulkdata/BILLSTATUS/115/hr/BILLSTATUS-115hr2382.xml"
}