{
  "actions": [
    {
      "acted_at": "2017-06-22", 
      "action_code": "Intro-H", 
      "references": [], 
      "text": "Introduced in House", 
      "type": "action"
    }, 
    {
      "acted_at": "2017-06-22", 
      "action_code": "H11100", 
      "committees": [
        "HSED"
      ], 
      "references": [], 
      "status": "REFERRED", 
      "text": "Referred to the House Committee on Education and the Workforce.", 
      "type": "referral"
    }
  ], 
  "amendments": [], 
  "bill_id": "hr3026-115", 
  "bill_type": "hr", 
  "by_request": false, 
  "committee_reports": [], 
  "committees": [
    {
      "activity": [
        "referral"
      ], 
      "committee": "House Education and the Workforce", 
      "committee_id": "HSED"
    }
  ], 
  "congress": "115", 
  "cosponsors": [
    {
      "bioguide_id": "B001296", 
      "district": "13", 
      "name": "Boyle, Brendan F.", 
      "original_cosponsor": true, 
      "sponsored_at": "2017-06-22", 
      "state": "PA", 
      "title": "Rep", 
      "withdrawn_at": null
    }, 
    {
      "bioguide_id": "D000624", 
      "district": "12", 
      "name": "Dingell, Debbie", 
      "original_cosponsor": false, 
      "sponsored_at": "2017-07-27", 
      "state": "MI", 
      "title": "Rep", 
      "withdrawn_at": null
    }, 
    {
      "bioguide_id": "G000559", 
      "district": "3", 
      "name": "Garamendi, John", 
      "original_cosponsor": true, 
      "sponsored_at": "2017-06-22", 
      "state": "CA", 
      "title": "Rep", 
      "withdrawn_at": null
    }, 
    {
      "bioguide_id": "K000381", 
      "district": "6", 
      "name": "Kilmer, Derek", 
      "original_cosponsor": false, 
      "sponsored_at": "2017-06-26", 
      "state": "WA", 
      "title": "Rep", 
      "withdrawn_at": null
    }, 
    {
      "bioguide_id": "P000613", 
      "district": "20", 
      "name": "Panetta, Jimmy", 
      "original_cosponsor": false, 
      "sponsored_at": "2017-07-27", 
      "state": "CA", 
      "title": "Rep", 
      "withdrawn_at": null
    }
  ], 
  "enacted_as": null, 
  "history": {
    "active": false, 
    "awaiting_signature": false, 
    "enacted": false, 
    "vetoed": false
  }, 
  "introduced_at": "2017-06-22", 
  "number": "3026", 
  "official_title": "To amend the Higher Education Act of 1965 to provide for a percentage of student loan forgiveness for public service employment, and for other purposes.", 
  "popular_title": null, 
  "related_bills": [], 
  "short_title": "Strengthening Loan Forgiveness for Public Servants Act", 
  "sponsor": {
    "bioguide_id": "S001193", 
    "district": "15", 
    "name": "Swalwell, Eric", 
    "state": "CA", 
    "title": "Rep", 
    "type": "person"
  }, 
  "status": "REFERRED", 
  "status_at": "2017-06-22", 
  "subjects": [
    "Education", 
    "Government employee pay, benefits, personnel management", 
    "Government information and archives", 
    "Health personnel", 
    "Higher education", 
    "Interest, dividends, interest rates", 
    "Law enforcement officers", 
    "Military personnel and dependents", 
    "Social work, volunteer service, charitable organizations", 
    "Student aid and college costs"
  ], 
  "subjects_top_term": "Education", 
  "summary": null, 
  "titles": [
    {
      "as": "introduced", 
      "is_for_portion": false, 
      "title": "Strengthening Loan Forgiveness for Public Servants Act", 
      "type": "short"
    }, 
    {
      "as": "introduced", 
      "is_for_portion": false, 
      "title": "Strengthening Loan Forgiveness for Public Servants Act", 
      "type": "short"
    }, 
    {
      "as": "introduced", 
      "is_for_portion": false, 
      "title": "To amend the Higher Education Act of 1965 to provide for a percentage of student loan forgiveness for public service employment, and for other purposes.", 
      "type": "official"
    }, 
    {
      "as": null, 
      "is_for_portion": false, 
      "title": "Strengthening Loan Forgiveness for Public Servants Act", 
      "type": "display"
    }
  ], 
  "updated_at": "2017-07-28T07:16:49Z", 
  "url": "https://www.gpo.gov/fdsys/bulkdata/BILLSTATUS/115/hr/BILLSTATUS-115hr3026.xml"
}