{
  "actions": [
    {
      "acted_at": "2017-06-27", 
      "action_code": "Intro-H", 
      "references": [], 
      "text": "Introduced in House", 
      "type": "action"
    }, 
    {
      "acted_at": "2017-06-27", 
      "action_code": "H11100", 
      "committees": [
        "HSGO"
      ], 
      "references": [], 
      "status": "REFERRED", 
      "text": "Referred to the House Committee on Oversight and Government Reform.", 
      "type": "referral"
    }
  ], 
  "amendments": [], 
  "bill_id": "hr3076-115", 
  "bill_type": "hr", 
  "by_request": false, 
  "committee_reports": [], 
  "committees": [
    {
      "activity": [
        "referral"
      ], 
      "committee": "House Oversight and Government Reform", 
      "committee_id": "HSGO"
    }
  ], 
  "congress": "115", 
  "cosponsors": [
    {
      "bioguide_id": "K000379", 
      "district": "4", 
      "name": "Kennedy, Joseph P., III", 
      "original_cosponsor": true, 
      "sponsored_at": "2017-06-27", 
      "state": "MA", 
      "title": "Rep", 
      "withdrawn_at": null
    }
  ], 
  "enacted_as": null, 
  "history": {
    "active": false, 
    "awaiting_signature": false, 
    "enacted": false, 
    "vetoed": false
  }, 
  "introduced_at": "2017-06-27", 
  "number": "3076", 
  "official_title": "To amend section 552a of title 5, United States Code (commonly referred to as the Privacy Act) to require agencies to accept electronic release forms, and for other purposes.", 
  "popular_title": null, 
  "related_bills": [], 
  "short_title": "Creating Advanced Streamlined Electronic Services (CASES) for Constituents Act of 2017", 
  "sponsor": {
    "bioguide_id": "G000577", 
    "district": "6", 
    "name": "Graves, Garret", 
    "state": "LA", 
    "title": "Rep", 
    "type": "person"
  }, 
  "status": "REFERRED", 
  "status_at": "2017-06-27", 
  "subjects": [
    "Government operations and politics"
  ], 
  "subjects_top_term": "Government operations and politics", 
  "summary": null, 
  "titles": [
    {
      "as": "introduced", 
      "is_for_portion": false, 
      "title": "Creating Advanced Streamlined Electronic Services (CASES) for Constituents Act of 2017", 
      "type": "short"
    }, 
    {
      "as": "introduced", 
      "is_for_portion": false, 
      "title": "Creating Advanced Streamlined Electronic Services (CASES) for Constituents Act of 2017", 
      "type": "short"
    }, 
    {
      "as": "introduced", 
      "is_for_portion": false, 
      "title": "To amend section 552a of title 5, United States Code (commonly referred to as the Privacy Act) to require agencies to accept electronic release forms, and for other purposes.", 
      "type": "official"
    }, 
    {
      "as": null, 
      "is_for_portion": false, 
      "title": "Creating Advanced Streamlined Electronic Services (CASES) for Constituents Act of 2017", 
      "type": "display"
    }
  ], 
  "updated_at": "2017-07-13T13:25:46Z", 
  "url": "https://www.gpo.gov/fdsys/bulkdata/BILLSTATUS/115/hr/BILLSTATUS-115hr3076.xml"
}